ckanext/__init__.py
ckanext/tiledmap/__init__.py
ckanext/tiledmap/config.py
ckanext/tiledmap/plugin.py
ckanext/tiledmap/lib/__init__.py
ckanext/tiledmap/lib/helpers.py
ckanext/tiledmap/lib/utils.py
ckanext/tiledmap/lib/validators.py
ckanext/tiledmap/routes/__init__.py
ckanext/tiledmap/routes/_helpers.py
ckanext/tiledmap/routes/map.py
ckanext/tiledmap/theme/assets/webassets.yml
ckanext/tiledmap/theme/assets/less/maps.less
ckanext/tiledmap/theme/assets/scripts/ckanfilterurl.js
ckanext/tiledmap/theme/assets/scripts/drawshape_control.js
ckanext/tiledmap/theme/assets/scripts/fullscreen_control.js
ckanext/tiledmap/theme/assets/scripts/map_view.js
ckanext/tiledmap/theme/assets/scripts/maptype_control.js
ckanext/tiledmap/theme/assets/scripts/minimap_control.js
ckanext/tiledmap/theme/assets/scripts/pointinfo_plugin.js
ckanext/tiledmap/theme/assets/scripts/sidebar_view.js
ckanext/tiledmap/theme/assets/scripts/tiledmap_module.js
ckanext/tiledmap/theme/assets/scripts/tooltip_plugin.js
ckanext/tiledmap/theme/assets/vendor/backbone/1.0.0/backbone.js
ckanext/tiledmap/theme/assets/vendor/jquery/1.7.1/jquery.js
ckanext/tiledmap/theme/assets/vendor/jquery/1.7.1/jquery.min.js
ckanext/tiledmap/theme/assets/vendor/leaflet/leaflet-src.js
ckanext/tiledmap/theme/assets/vendor/leaflet/leaflet.css
ckanext/tiledmap/theme/assets/vendor/leaflet/leaflet.js
ckanext/tiledmap/theme/assets/vendor/leaflet.draw/leaflet.draw-src.js
ckanext/tiledmap/theme/assets/vendor/leaflet.draw/leaflet.draw.css
ckanext/tiledmap/theme/assets/vendor/leaflet.minimap/Control.MiniMap.css
ckanext/tiledmap/theme/assets/vendor/leaflet.minimap/Control.MiniMap.js
ckanext/tiledmap/theme/assets/vendor/leaflet.minimap/LICENSE.txt
ckanext/tiledmap/theme/assets/vendor/leaflet.minimap/readme.md
ckanext/tiledmap/theme/assets/vendor/leaflet.utfgrid/leaflet.utfgrid.js
ckanext/tiledmap/theme/assets/vendor/leaflet.utfgrid/leaflet.utfgrid.queue.js
ckanext/tiledmap/theme/assets/vendor/mustache/0.5.0-dev/mustache.js
ckanext_versioned_tiledmap-2.3.4.dist-info/licenses/LICENSE
ckanext_versioned_tiledmap-2.3.4.dist-info/METADATA
ckanext_versioned_tiledmap-2.3.4.dist-info/WHEEL
ckanext_versioned_tiledmap-2.3.4.dist-info/entry_points.txt
ckanext_versioned_tiledmap-2.3.4.dist-info/top_level.txt
ckanext_versioned_tiledmap-2.3.4.dist-info/RECORD
