Metadata-Version: 2.4
Name: ckanext-versioned-tiledmap
Version: 2.3.4
Summary: A CKAN extension with a map view for versioned-datastore backed resources.
Author-email: Natural History Museum <data@nhm.ac.uk>
License: GPL-3.0-or-later
Project-URL: repository, https://github.com/NaturalHistoryMuseum/ckanext-versioned-tiledmap
Project-URL: changelog, https://github.com/NaturalHistoryMuseum/ckanext-versioned-tiledmap/blob/main/CHANGELOG.md
Keywords: CKAN,data,versioned_tiledmap
Classifier: Development Status :: 5 - Production/Stable
Classifier: License :: OSI Approved :: GNU General Public License v3 (GPLv3)
Classifier: Programming Language :: Python
Classifier: Programming Language :: Python :: 3 :: Only
Classifier: Programming Language :: Python :: 3.6
Classifier: Programming Language :: Python :: 3.7
Classifier: Programming Language :: Python :: 3.8
Requires-Python: >=3.6
License-File: LICENSE
Requires-Dist: ckanext-versioned-datastore>=3.7.0
Requires-Dist: cachetools>=4.2.4
Requires-Dist: ckantools>=0.4.2
Provides-Extra: test
Requires-Dist: mock; extra == "test"
Requires-Dist: pytest>=4.6.5; extra == "test"
Requires-Dist: pytest-cov>=2.7.1; extra == "test"
Requires-Dist: coveralls; extra == "test"
Dynamic: license-file
